Metadata-Version: 1.1
Name: django-preventconcurrentlogins
Version: 0.8.1
Summary: Django middleware that prevents multiple concurrent logins.
Home-page: https://github.com/pcraston/django-preventconcurrentlogins
Author: Patrick Craston
Author-email: patrick@craston.com
License: MIT License
Platform: UNKNOWN
Classifier: Environment :: Web Environment
Classifier: Framework :: Django
Classifier: Intended Audience :: Developers
Classifier: License :: OSI Approved :: MIT License
Classifier: Operating System :: OS Independent
Classifier: Programming Language :: Python
Classifier: Programming Language :: Python :: 2.7
Classifier: Topic :: Internet :: WWW/HTTP
Classifier: Topic :: Internet :: WWW/HTTP :: Dynamic Content
